mcpcommander/__init__.py
mcpcommander/__main__.py
mcpcommander/py.typed
mcpcommander/cli/__init__.py
mcpcommander/cli/main.py
mcpcommander/core/__init__.py
mcpcommander/core/config.py
mcpcommander/core/editor_handlers.py
mcpcommander/core/manager.py
mcpcommander/schemas/__init__.py
mcpcommander/schemas/config_schema.py
mcpcommander/utils/__init__.py
mcpcommander/utils/cli_examples.py
mcpcommander/utils/config_parser.py
mcpcommander/utils/discovery.py
mcpcommander/utils/errors.py
mcpcommander/utils/logger.py
mcpcommander/utils/paths.py
mcp_commander-0.1.2.dist-info/METADATA
mcp_commander-0.1.2.dist-info/WHEEL
mcp_commander-0.1.2.dist-info/entry_points.txt
mcp_commander-0.1.2.dist-info/top_level.txt
mcp_commander-0.1.2.dist-info/RECORD
