Metadata-Version: 2.4
Name: mcp-commander
Version: 0.1.2
Summary: Cross-platform command-line tool for managing MCP (Model Context Protocol) servers across editors
Author-email: Evandro Camargo <evandro@camargo.uk>
Maintainer-email: Evandro Camargo <evandro@camargo.uk>
License: Apache-2.0
Project-URL: Homepage, https://github.com/nmindz/mcp-commander
Project-URL: Repository, https://github.com/nmindz/mcp-commander
Project-URL: Issues, https://github.com/nmindz/mcp-commander/issues
Project-URL: Documentation, https://github.com/nmindz/mcp-commander#readme
Keywords: mcp,model-context-protocol,claude,cursor,vscode,cli
Classifier: Development Status :: 4 - Beta
Classifier: Environment :: Console
Classifier: Intended Audience :: Developers
Classifier: Intended Audience :: System Administrators
Classifier: License :: OSI Approved :: Apache Software License
Classifier: Operating System :: OS Independent
Classifier: Operating System :: MacOS
Classifier: Operating System :: Microsoft :: Windows
Classifier: Operating System :: POSIX :: Linux
Classifier: Programming Language :: Python :: 3
Classifier: Programming Language :: Python :: 3.12
Classifier: Programming Language :: Python :: 3 :: Only
Classifier: Topic :: Software Development
Classifier: Topic :: System :: Systems Administration
Classifier: Topic :: Terminals
Classifier: Topic :: Utilities
Classifier: Typing :: Typed
Requires-Python: >=3.12
Requires-Dist: colorama>=0.4.6
Requires-Dist: pydantic>=2.0.0
Requires-Dist: typer>=0.9.0
Requires-Dist: rich>=13.0.0
Provides-Extra: dev
Requires-Dist: pytest>=7.4.0; extra == "dev"
Requires-Dist: pytest-cov>=4.1.0; extra == "dev"
Requires-Dist: pytest-mock>=3.11.0; extra == "dev"
Requires-Dist: mypy>=1.5.0; extra == "dev"
Requires-Dist: ruff>=0.1.0; extra == "dev"
Requires-Dist: pre-commit>=3.0.0; extra == "dev"
Provides-Extra: build
Requires-Dist: build>=0.10.0; extra == "build"
Requires-Dist: twine>=4.0.0; extra == "build"
